htmlstr/__init__.py
htmlstr/core.py
htmlstr-0.1.0.dist-info/METADATA
htmlstr-0.1.0.dist-info/WHEEL
htmlstr-0.1.0.dist-info/top_level.txt
htmlstr-0.1.0.dist-info/RECORD
