Metadata-Version: 2.4
Name: htmlstr
Version: 0.1.0
Summary: Make HTML structured.
License-Expression: MIT
Classifier: Programming Language :: Python :: Implementation :: CPython
Classifier: Programming Language :: Python :: Implementation :: PyPy
Requires-Python: >=3.8
Requires-Dist: selectolax
